llama_index/tools/database/__init__.py
llama_index/tools/database/base.py
llama_index_tools_database-0.4.1.dist-info/METADATA
llama_index_tools_database-0.4.1.dist-info/WHEEL
llama_index_tools_database-0.4.1.dist-info/licenses/LICENSE
llama_index_tools_database-0.4.1.dist-info/RECORD
