Metadata-Version: 2.4
Name: llama-index-tools-database
Version: 0.4.1
Summary: llama-index tools database integration
Author-email: Your Name <you@example.com>
Maintainer: ajhofmann
License-Expression: MIT
License-File: LICENSE
Keywords: aws rds,postgres,snowflake,sql
Requires-Python: <4.0,>=3.9
Requires-Dist: llama-index-core<0.15,>=0.13.0
